LICENSE
MANIFEST.in
README.rst
setup.py
django_sidebar.egg-info/PKG-INFO
django_sidebar.egg-info/SOURCES.txt
django_sidebar.egg-info/dependency_links.txt
django_sidebar.egg-info/not-zip-safe
django_sidebar.egg-info/top_level.txt
sidebar/__init__.py
sidebar/admin.py
sidebar/base.py
sidebar/forms.py
sidebar/models.py
sidebar/urls.py
sidebar/utils.py
sidebar/views.py
sidebar/locale/de/LC_MESSAGES/django.mo
sidebar/locale/de/LC_MESSAGES/django.po
sidebar/static/admin/sidebar/css/sidebar.css
sidebar/static/admin/sidebar/images/add.png
sidebar/static/admin/sidebar/images/icons.png
sidebar/static/admin/sidebar/images/loading.gif
sidebar/static/admin/sidebar/js/jquery-1.7.1.min.js
sidebar/static/admin/sidebar/js/jquery-ui-1.8.17.custom.min.js
sidebar/static/admin/sidebar/js/sidebar.js
sidebar/templates/admin/sidebar/sidebar/change_form.html
sidebar/templates/admin/sidebar/sidebar/sidebar_builder.html
sidebar/templates/admin/sidebar/sidebar/widgets.html
sidebar/templatetags/__init__.py
sidebar/templatetags/sidebar_tags.py
sidebar/widget_sample/text.py