Metadata-Version: 1.0
Name: django-sidebar
Version: 0.1.3
Summary: Dynamic Sidebar creation for Django. Easily create and manage sidebar from Django Admin.
Home-page: https://github.com/ekaputra07/django-sidebar
Author: Eka Putra
Author-email: ekaputra@balitechy.com
License: BSD
Download-URL: https://github.com/ekaputra07/django-sidebar/downloads
Platform: UNKNOWN
Classifier: Development Status :: 3 - Alpha
Classifier: Framework :: Django
Classifier: Intended Audience :: Developers
Classifier: License :: OSI Approved :: BSD License
Classifier: Operating System :: OS Independent
Classifier: Programming Language :: Python
Classifier: Topic :: Internet :: WWW/HTTP
